{"id":"2L49fSf5MQKeLHmGuif4WM7REccy4o4wLgN7rJZWBdG7","bump":255,"version":19,"root":[178,134,165,174,122,59,156,81,225,208,237,245,172,23,202,33,187,249,100,88,103,93,12,95,219,68,12,238,159,147,153,230],"mint":"JUPyiwrYJFskUPiHa7hkeR8VUtAeFoSYbKedZNsDvCN","tokenVault":"DW4o7iPtd95UMjpo26kgjcfZC8X2KifBSaMXDBJ2Lbre","maxTotalClaim":12373150000000,"maxNumNodes":12000,"totalAmountClaimed":0,"numNodesClaimed":0,"startTs":1709186258,"endTs":1711691858,"clawbackStartTs":1722438000,"clawbackReciever":"K6U4dQ8jANMEqQQycXYiDcf3172NGefpQBzdDbavQbA","admin":"DHLXnJdACTY83yKwnUkeoDjqi4QBbsYGa1v8tJL76ViX","clawedBack":false,"enableSlot":245287622,"closable":true,"buffer0":[0,0,0,0,0,0,0,0,0,0,0,0,0,0,0,0,0,0,0,0,0,0,0,0,0,0,0,0,0,0,0,0],"buffer1":[0,0,0,0,0,0,0,0,0,0,0,0,0,0,0,0,0,0,0,0,0,0,0,0,0,0,0,0,0,0,0,0],"buffer2":[0,0,0,0,0,0,0,0,0,0,0,0,0,0,0,0,0,0,0,0,0,0,0,0,0,0,0,0,0,0,0,0]}