{"id":"6U64stZcuPR2PExuA7higtQ4jEzGJRb49MBD5ZA8pQ5r","bump":255,"version":64,"root":[33,125,227,181,78,173,100,246,207,253,138,103,35,12,0,23,157,181,213,131,81,192,221,228,58,88,125,231,204,154,163,187],"mint":"JUPyiwrYJFskUPiHa7hkeR8VUtAeFoSYbKedZNsDvCN","tokenVault":"ciFzinw62j2FwFmv13RqCUdHQFFskywRZpJ79ov5SbA","maxTotalClaim":12078900000000,"maxNumNodes":12000,"totalAmountClaimed":0,"numNodesClaimed":0,"startTs":1709186258,"endTs":1711691858,"clawbackStartTs":1722438000,"clawbackReciever":"K6U4dQ8jANMEqQQycXYiDcf3172NGefpQBzdDbavQbA","admin":"DHLXnJdACTY83yKwnUkeoDjqi4QBbsYGa1v8tJL76ViX","clawedBack":false,"enableSlot":245287622,"closable":true,"buffer0":[0,0,0,0,0,0,0,0,0,0,0,0,0,0,0,0,0,0,0,0,0,0,0,0,0,0,0,0,0,0,0,0],"buffer1":[0,0,0,0,0,0,0,0,0,0,0,0,0,0,0,0,0,0,0,0,0,0,0,0,0,0,0,0,0,0,0,0],"buffer2":[0,0,0,0,0,0,0,0,0,0,0,0,0,0,0,0,0,0,0,0,0,0,0,0,0,0,0,0,0,0,0,0]}