{"id":"eGdi9yWbbTerGauVm5fMq4YDtUaFcCE31fzrWwua1Sa","bump":255,"version":71,"root":[132,199,234,9,52,223,60,75,32,174,251,82,4,240,76,130,63,20,83,43,127,174,18,52,40,230,132,123,95,87,217,66],"mint":"WENWENvqqNya429ubCdR81ZmD69brwQaaBYY6p3LCpk","tokenVault":"52S98tcp6FKBtnbUV8nthjzoYrwpPonpNBZVJ9meGrZj","maxTotalClaim":772382400000000,"maxNumNodes":12000,"totalAmountClaimed":0,"numNodesClaimed":0,"startTs":1706205600,"endTs":1706281200,"clawbackStartTs":1706540400,"clawbackReciever":"EyDdMHQqXa9C8uKdExSBBbZFBMuKn3vA2MdtA6rubVVY","admin":"JADaUV8kvDpDbJr55wxXJHVaBS3VCj8thZZHjfeuCVLd","clawedBack":true,"enableSlot":244248510,"closable":true,"buffer0":[0,0,0,0,0,0,0,0,0,0,0,0,0,0,0,0,0,0,0,0,0,0,0,0,0,0,0,0,0,0,0,0],"buffer1":[0,0,0,0,0,0,0,0,0,0,0,0,0,0,0,0,0,0,0,0,0,0,0,0,0,0,0,0,0,0,0,0],"buffer2":[0,0,0,0,0,0,0,0,0,0,0,0,0,0,0,0,0,0,0,0,0,0,0,0,0,0,0,0,0,0,0,0]}